{"reviews":[{"collection_tag":"VIAJERO POR NEGOCIOS","comments":"El depto. es muy bueno, la cama es confortable y todo en la casa funciona a la perfección. El edificio es muy tranquilo y tiene seguridad casi todo el tiempo. \nLa privacidad es lo mejor del lugar.","created_at":"2017-11-28T16:08:02Z","id":215236423,"language":"es","localized_date":"Noviembre de 2017","response":"","reviewee":{"deleted":false,"first_name":"María Alicia Y Mauricio","host_name":"María Alicia Y Mauricio","id":28474161,"is_superhost":true,"picture_url":"https://a0.muscache.com/im/pictures/d9cd434e-f63b-4b5f-bf76-07ac7709ab6d.jpg?aki_policy=profile_x_medium","profile_path":"/users/show/28474161"},"reviewer":{"deleted":false,"first_name":"Gabriel","host_name":"Gabriel","id":60280003,"is_superhost":false,"picture_url":"https://a0.muscache.com/im/pictures/user/5bc978bb-c44e-4ef5-b5cc-b239f8f7f624.jpg?aki_policy=profile_x_medium","profile_path":"/users/show/60280003"}},{"collection_tag":"VIAJERO EN FAMILIA","comments":"Muy recomendable!","created_at":"2017-11-19T18:42:15Z","id":212974515,"language":"es","localized_date":"Noviembre de 2017","response":"","reviewee":{"deleted":false,"first_name":"María Alicia Y Mauricio","host_name":"María Alicia Y Mauricio","id":28474161,"is_superhost":true,"picture_url":"https://a0.muscache.com/im/pictures/d9cd434e-f63b-4b5f-bf76-07ac7709ab6d.jpg?aki_policy=profile_x_medium","profile_path":"/users/show/28474161"},"reviewer":{"deleted":false,"first_name":"Ana","host_name":"Ana","id":7897813,"is_superhost":false,"picture_url":"https://a0.muscache.com/im/pictures/42a0aef4-ee05-4ccb-bb8e-065f01da2002.jpg?aki_policy=profile_x_medium","profile_path":"/users/show/7897813"}},{"collection_tag":null,"comments":"Todo muy bueno. Ubicación, comodidad y Alicia muy ATENTA en todo. Una sola palabra para describirlo. PERFECTO.","created_at":"2017-09-17T16:41:30Z","id":194769345,"language":"es","localized_date":"Septiembre de 2017","response":"","reviewee":{"deleted":false,"first_name":"María Alicia Y Mauricio","host_name":"María Alicia Y Mauricio","id":28474161,"is_superhost":true,"picture_url":"https://a0.muscache.com/im/pictures/d9cd434e-f63b-4b5f-bf76-07ac7709ab6d.jpg?aki_policy=profile_x_medium","profile_path":"/users/show/28474161"},"reviewer":{"deleted":false,"first_name":"Joel","host_name":"Joel","id":146748607,"is_superhost":false,"picture_url":"https://a0.muscache.com/im/pictures/user/8c185400-cacc-4bf1-a974-edbfb903a2af.jpg?aki_policy=profile_x_medium","profile_path":"/users/show/146748607"}},{"collection_tag":"VIAJERO EN FAMILIA","comments":"La ubicación excelente en pleno centro cerca de todo. El depto impecable con toallas, sábanas, secador, cocina completa. Muy recomendable.","created_at":"2017-09-11T18:20:26Z","id":192919408,"language":"es","localized_date":"Septiembre de 2017","response":"","reviewee":{"deleted":false,"first_name":"María Alicia Y Mauricio","host_name":"María Alicia Y Mauricio","id":28474161,"is_superhost":true,"picture_url":"https://a0.muscache.com/im/pictures/d9cd434e-f63b-4b5f-bf76-07ac7709ab6d.jpg?aki_policy=profile_x_medium","profile_path":"/users/show/28474161"},"reviewer":{"deleted":false,"first_name":"Eugenia","host_name":"Eugenia","id":125006270,"is_superhost":false,"picture_url":"https://a0.muscache.com/im/pictures/fe0ff133-0901-45ac-83b1-3904f602428c.jpg?aki_policy=profile_x_medium","profile_path":"/users/show/125006270"}},{"collection_tag":null,"comments":"Muy atentos, muy buena ubicación y servicio","created_at":"2017-08-27T17:45:06Z","id":187720974,"language":"es","localized_date":"Agosto de 2017","response":"","reviewee":{"deleted":false,"first_name":"María Alicia Y Mauricio","host_name":"María Alicia Y Mauricio","id":28474161,"is_superhost":true,"picture_url":"https://a0.muscache.com/im/pictures/d9cd434e-f63b-4b5f-bf76-07ac7709ab6d.jpg?aki_policy=profile_x_medium","profile_path":"/users/show/28474161"},"reviewer":{"deleted":false,"first_name":"Mariela","host_name":"Mariela","id":143395533,"is_superhost":false,"picture_url":"https://a0.muscache.com/im/pictures/9a3a325a-c61b-4cac-9d38-2b95375f8e44.jpg?aki_policy=profile_x_medium","profile_path":"/users/show/143395533"}},{"collection_tag":"VIAJERO POR NEGOCIOS","comments":"Diez puntos todo!! Muchas gracias!","created_at":"2017-08-25T17:18:48Z","id":186795697,"language":"es","localized_date":"Agosto de 2017","response":"","reviewee":{"deleted":false,"first_name":"María Alicia Y Mauricio","host_name":"María Alicia Y Mauricio","id":28474161,"is_superhost":true,"picture_url":"https://a0.muscache.com/im/pictures/d9cd434e-f63b-4b5f-bf76-07ac7709ab6d.jpg?aki_policy=profile_x_medium","profile_path":"/users/show/28474161"},"reviewer":{"deleted":false,"first_name":"Sergio","host_name":"Sergio","id":102112510,"is_superhost":false,"picture_url":"https://a0.muscache.com/im/pictures/user/4cd3268a-77dd-4d2a-990d-1d8e72c0c961.jpg?aki_policy=profile_x_medium","profile_path":"/users/show/102112510"}},{"collection_tag":null,"comments":"Excelente departamento con muy buena ubicación, la atención de sus dueños fue impecable.","created_at":"2017-08-21T16:27:39Z","id":185389345,"language":"es","localized_date":"Agosto de 2017","response":"","reviewee":{"deleted":false,"first_name":"María Alicia Y Mauricio","host_name":"María Alicia Y Mauricio","id":28474161,"is_superhost":true,"picture_url":"https://a0.muscache.com/im/pictures/d9cd434e-f63b-4b5f-bf76-07ac7709ab6d.jpg?aki_policy=profile_x_medium","profile_path":"/users/show/28474161"},"reviewer":{"deleted":false,"first_name":"Fabiana","host_name":"Fabiana","id":92189034,"is_superhost":false,"picture_url":"https://a0.muscache.com/im/pictures/585ba67d-0a9a-4298-bd97-15a7f84cb266.jpg?aki_policy=profile_x_medium","profile_path":"/users/show/92189034"}},{"collection_tag":null,"comments":"Estuve cuatro días con mis padres en el departamento. Es super recomendable. María Alicia nos recibió muy bien, fue muy fácil acordar con ella nuestra llegada. El alojamiento tiene una ubicación excelente, muy céntrico. Dejamos el auto estacionado en la calle y nos movimos casi todo el tiempo caminando. En pleno julio la calefacción funcionaba muy bien. Estuvimos muy cómodos.\nMuchas gracias María Alicia, fue un gusto! Seguramente volveremos.","created_at":"2017-07-16T16:52:18Z","id":170962168,"language":"es","localized_date":"Julio de 2017","response":"","reviewee":{"deleted":false,"first_name":"María Alicia Y Mauricio","host_name":"María Alicia Y Mauricio","id":28474161,"is_superhost":true,"picture_url":"https://a0.muscache.com/im/pictures/d9cd434e-f63b-4b5f-bf76-07ac7709ab6d.jpg?aki_policy=profile_x_medium","profile_path":"/users/show/28474161"},"reviewer":{"deleted":false,"first_name":"Luisa","host_name":"Luisa","id":11628428,"is_superhost":false,"picture_url":"https://a0.muscache.com/im/users/11628428/profile_pic/1443388602/original.jpg?aki_policy=profile_x_medium","profile_path":"/users/show/11628428"}},{"collection_tag":"VIAJERO EN FAMILIA","comments":"Muy buena atencion. El departamento es moderno, limpio y centrico.","created_at":"2017-05-02T18:35:00Z","id":149139968,"language":"es","localized_date":"Mayo de 2017","response":"","reviewee":{"deleted":false,"first_name":"María Alicia Y Mauricio","host_name":"María Alicia Y Mauricio","id":28474161,"is_superhost":true,"picture_url":"https://a0.muscache.com/im/pictures/d9cd434e-f63b-4b5f-bf76-07ac7709ab6d.jpg?aki_policy=profile_x_medium","profile_path":"/users/show/28474161"},"reviewer":{"deleted":false,"first_name":"Jose Luis","host_name":"Jose Luis","id":126784994,"is_superhost":false,"picture_url":"https://a0.muscache.com/im/pictures/7898fbc9-5fde-4d19-b4a9-4352e4aa0404.jpg?aki_policy=profile_x_medium","profile_path":"/users/show/126784994"}},{"collection_tag":null,"comments":"Maria Alicia es muy calida, simpatica y buena anfitriona. La comunicacion con ambos previa a nuestra llegada fue excelente. Super recomendable!!! esperamos volver pronto.","created_at":"2017-04-23T14:39:26Z","id":146687004,"language":"es","localized_date":"Abril de 2017","response":"","reviewee":{"deleted":false,"first_name":"María Alicia Y Mauricio","host_name":"María Alicia Y Mauricio","id":28474161,"is_superhost":true,"picture_url":"https://a0.muscache.com/im/pictures/d9cd434e-f63b-4b5f-bf76-07ac7709ab6d.jpg?aki_policy=profile_x_medium","profile_path":"/users/show/28474161"},"reviewer":{"deleted":false,"first_name":"Natalia","host_name":"Natalia","id":45108233,"is_superhost":false,"picture_url":"https://a0.muscache.com/im/users/45108233/profile_pic/1443234731/original.jpg?aki_policy=profile_x_medium","profile_path":"/users/show/45108233"}},{"collection_tag":null,"comments":"Muy bueno el departamento y excelente atención.","created_at":"2017-04-16T14:21:37Z","id":144755081,"language":"es","localized_date":"Abril de 2017","response":"","reviewee":{"deleted":false,"first_name":"María Alicia Y Mauricio","host_name":"María Alicia Y Mauricio","id":28474161,"is_superhost":true,"picture_url":"https://a0.muscache.com/im/pictures/d9cd434e-f63b-4b5f-bf76-07ac7709ab6d.jpg?aki_policy=profile_x_medium","profile_path":"/users/show/28474161"},"reviewer":{"deleted":false,"first_name":"Gustavo Javier","host_name":"Gustavo Javier","id":123645240,"is_superhost":false,"picture_url":"https://a0.muscache.com/im/pictures/92baa739-2498-4ab8-ad97-f8d4a4d7683a.jpg?aki_policy=profile_x_medium","profile_path":"/users/show/123645240"}},{"collection_tag":null,"comments":"Alicia es una anfitriona de lujo! Como su departamento tuvo inconvenientes luego de realizada la reserva nos busco otro lugar en donde hospedarnos con los requsitos solicitados para que no dejarnos en banda. Super recomendable!","created_at":"2017-04-04T14:26:54Z","id":141743516,"language":"es","localized_date":"Abril de 2017","response":"","reviewee":{"deleted":false,"first_name":"María Alicia Y Mauricio","host_name":"María Alicia Y Mauricio","id":28474161,"is_superhost":true,"picture_url":"https://a0.muscache.com/im/pictures/d9cd434e-f63b-4b5f-bf76-07ac7709ab6d.jpg?aki_policy=profile_x_medium","profile_path":"/users/show/28474161"},"reviewer":{"deleted":false,"first_name":"Martina","host_name":"Martina","id":31681127,"is_superhost":false,"picture_url":"https://a0.muscache.com/im/pictures/03a54ff9-dcd0-4527-8f25-425b2995c87b.jpg?aki_policy=profile_x_medium","profile_path":"/users/show/31681127"}},{"collection_tag":null,"comments":"En cuanto al departamento, cómodo y muy bien ubicado, Equipado con todo lo necesario. Alicia súper atenta y predispuesta. ","created_at":"2017-02-26T14:09:27Z","id":134229707,"language":"es","localized_date":"Febrero de 2017","response":"","reviewee":{"deleted":false,"first_name":"María Alicia Y Mauricio","host_name":"María Alicia Y Mauricio","id":28474161,"is_superhost":true,"picture_url":"https://a0.muscache.com/im/pictures/d9cd434e-f63b-4b5f-bf76-07ac7709ab6d.jpg?aki_policy=profile_x_medium","profile_path":"/users/show/28474161"},"reviewer":{"deleted":false,"first_name":"Pamela","host_name":"Pamela","id":49575746,"is_superhost":false,"picture_url":"https://a0.muscache.com/im/pictures/0ef8e4c0-a24e-4067-bbd3-1b2005e7ea3f.jpg?aki_policy=profile_x_medium","profile_path":"/users/show/49575746"}},{"collection_tag":null,"comments":"Nos hemos sentido perfecto durante nuestra estadia. Rapidamente nos contactamos con Maria Alicia y coordinamos nuestra llegada. El dpto es un lujo. Comodo, muy bien ubicado y acogedor. Muchisimas gracias.","created_at":"2016-11-28T14:40:46Z","id":116214963,"language":"es","localized_date":"Noviembre de 2016","response":"","reviewee":{"deleted":false,"first_name":"María Alicia Y Mauricio","host_name":"María Alicia Y Mauricio","id":28474161,"is_superhost":true,"picture_url":"https://a0.muscache.com/im/pictures/d9cd434e-f63b-4b5f-bf76-07ac7709ab6d.jpg?aki_policy=profile_x_medium","profile_path":"/users/show/28474161"},"reviewer":{"deleted":false,"first_name":"Federico","host_name":"Federico","id":46640443,"is_superhost":false,"picture_url":"https://a0.muscache.com/im/pictures/3ab713cf-3f66-4d66-8bb2-4b86c0ddbe88.jpg?aki_policy=profile_x_medium","profile_path":"/users/show/46640443"}},{"collection_tag":null,"comments":"Excelente! El Dpto es tal cual se lo describe, además de ser muy tranquilo a pesar de estar en una zona bien céntrica. Estuvieron muy atentos antes y durante la estadía. Recomendado!!","created_at":"2016-10-30T13:10:36Z","id":111232176,"language":"es","localized_date":"Octubre de 2016","response":"","reviewee":{"deleted":false,"first_name":"María Alicia Y Mauricio","host_name":"María Alicia Y Mauricio","id":28474161,"is_superhost":true,"picture_url":"https://a0.muscache.com/im/pictures/d9cd434e-f63b-4b5f-bf76-07ac7709ab6d.jpg?aki_policy=profile_x_medium","profile_path":"/users/show/28474161"},"reviewer":{"deleted":false,"first_name":"Dario","host_name":"Dario","id":29392168,"is_superhost":true,"picture_url":"https://a0.muscache.com/im/pictures/7ad0a1f7-cc84-4664-b198-16f6ce593d31.jpg?aki_policy=profile_x_medium","profile_path":"/users/show/29392168"}},{"collection_tag":null,"comments":"Excelente desde la atención hasta el departamento que se encuentra muy bien ubicado en zona céntrica y tiene todas las comodidades, las fotos no le hacen justicia, verdaderamente es muy espacioso e iluminado. \r\n \r\nImpecable limpieza y estado de los muebles. \r\n\r\nMuy flexibles con el horario de entrada y salida. \r\n","created_at":"2016-02-13T20:29:09Z","id":62318692,"language":"es","localized_date":"Febrero de 2016","response":"","reviewee":{"deleted":false,"first_name":"María Alicia Y Mauricio","host_name":"María Alicia Y Mauricio","id":28474161,"is_superhost":true,"picture_url":"https://a0.muscache.com/im/pictures/d9cd434e-f63b-4b5f-bf76-07ac7709ab6d.jpg?aki_policy=profile_x_medium","profile_path":"/users/show/28474161"},"reviewer":{"deleted":false,"first_name":"Carlos","host_name":"Carlos","id":58084622,"is_superhost":false,"picture_url":"https://a0.muscache.com/im/pictures/45f5fb56-fc6e-4379-bbfc-ae343f572527.jpg?aki_policy=profile_x_medium","profile_path":"/users/show/58084622"}},{"collection_tag":null,"comments":"Excelente el departamento, muy bien ubicado, muy lindo y bien cuidado. Muy recomendable. Gracias Mauricio, has sido muy amable con nosotros!","created_at":"2015-07-13T15:03:20Z","id":38169414,"language":"es","localized_date":"Julio de 2015","response":"","reviewee":{"deleted":false,"first_name":"María Alicia Y Mauricio","host_name":"María Alicia Y Mauricio","id":28474161,"is_superhost":true,"picture_url":"https://a0.muscache.com/im/pictures/d9cd434e-f63b-4b5f-bf76-07ac7709ab6d.jpg?aki_policy=profile_x_medium","profile_path":"/users/show/28474161"},"reviewer":{"deleted":false,"first_name":"Alvaro","host_name":"Alvaro","id":297991,"is_superhost":false,"picture_url":"https://a0.muscache.com/im/pictures/9dd86795-3806-4a11-b47c-1ae02cc71adf.jpg?aki_policy=profile_x_medium","profile_path":"/users/show/297991"}},{"collection_tag":null,"comments":"Dificil decir lo que más me gustó porque me gustó absolutamente todo: localizacion, limpieza, comunicacion, cuidado, confort, enfin inmejorable .... super hiper recomendable!","created_at":"2018-01-04T16:54:01Z","id":224842568,"language":"es","localized_date":"Enero de 2018","response":"","reviewee":{"deleted":false,"first_name":"María Alicia Y Mauricio","host_name":"María Alicia Y Mauricio","id":28474161,"is_superhost":true,"picture_url":"https://a0.muscache.com/im/pictures/d9cd434e-f63b-4b5f-bf76-07ac7709ab6d.jpg?aki_policy=profile_x_medium","profile_path":"/users/show/28474161"},"reviewer":{"deleted":false,"first_name":"Monica","host_name":"Monica","id":145630943,"is_superhost":false,"picture_url":"https://a0.muscache.com/im/pictures/2bf86ff0-d908-4deb-aa9f-f0ea7fceab44.jpg?aki_policy=profile_x_medium","profile_path":"/users/show/145630943"}},{"collection_tag":"VIAJERO EN FAMILIA","comments":"El apartamento es muy cómodo, está en muy buenas condiciones, y tiene una ubicación excelente. En el edificio hay portero las 24hs que siempre fueron muy serviciales para darnos indicaciones relativas a la ciudad.\nEl trato con los anfitriones fue muy bueno.\nCompletamente recomendable.","created_at":"2017-07-10T18:21:17Z","id":168904482,"language":"es","localized_date":"Julio de 2017","response":"","reviewee":{"deleted":false,"first_name":"María Alicia Y Mauricio","host_name":"María Alicia Y Mauricio","id":28474161,"is_superhost":true,"picture_url":"https://a0.muscache.com/im/pictures/d9cd434e-f63b-4b5f-bf76-07ac7709ab6d.jpg?aki_policy=profile_x_medium","profile_path":"/users/show/28474161"},"reviewer":{"deleted":false,"first_name":"Alvaro","host_name":"Alvaro","id":36375517,"is_superhost":false,"picture_url":"https://a0.muscache.com/im/users/36375517/profile_pic/1435026453/original.jpg?aki_policy=profile_x_medium","profile_path":"/users/show/36375517"}},{"collection_tag":null,"comments":"El alojamiento de María Alicia es perfecto! Ella fue muy amable y dispuesta a comunicarse. El departamento es amplio y con una ubicación perfecta. Totalmente recomendable","created_at":"2016-12-03T11:18:09Z","id":116770535,"language":"es","localized_date":"Diciembre de 2016","response":"","reviewee":{"deleted":false,"first_name":"María Alicia Y Mauricio","host_name":"María Alicia Y Mauricio","id":28474161,"is_superhost":true,"picture_url":"https://a0.muscache.com/im/pictures/d9cd434e-f63b-4b5f-bf76-07ac7709ab6d.jpg?aki_policy=profile_x_medium","profile_path":"/users/show/28474161"},"reviewer":{"deleted":false,"first_name":"Francisca","host_name":"Francisca","id":40730359,"is_superhost":false,"picture_url":"https://a0.muscache.com/im/users/40730359/profile_pic/1438899399/original.jpg?aki_policy=profile_x_medium","profile_path":"/users/show/40730359"}},{"collection_tag":null,"comments":"fuimos recibidos por la hermana de mauricio, ya nos estaba esperando,el departamento muy bonito,muy limpio,linda vista y amplio,seguridad los fin de semana,lo recomiendo ampliamente,no se van a arrepentir,todas las comodidades,gracias maria por todo,cuando volvamos a rio cuarto van a ser la primera opcion,gracias!!","created_at":"2016-05-23T11:22:20Z","id":75841646,"language":"es","localized_date":"Mayo de 2016","response":"Gracias a ustedes!","reviewee":{"deleted":false,"first_name":"María Alicia Y Mauricio","host_name":"María Alicia Y Mauricio","id":28474161,"is_superhost":true,"picture_url":"https://a0.muscache.com/im/pictures/d9cd434e-f63b-4b5f-bf76-07ac7709ab6d.jpg?aki_policy=profile_x_medium","profile_path":"/users/show/28474161"},"reviewer":{"deleted":false,"first_name":"Daniel","host_name":"Daniel","id":26903891,"is_superhost":false,"picture_url":"https://a0.muscache.com/im/pictures/c54d7e3c-6cf7-4c60-9cf8-8735db7ecf51.jpg?aki_policy=profile_x_medium","profile_path":"/users/show/26903891"}},{"collection_tag":null,"comments":"Excelente anfitrión!  Fuimos recibidos con muy buena onda por Alicia (hermana de Mauricio).  \r\nEl apartamento está excelente.  No pudimos disfrutarlo por mucho tiempo, porque lo usamos sólo como parada para dormir en nuestro road trip (Mendoza-Montevideo).\r\nA pesar de no tener cochera, pudimos dormir tranquilos dejando el auto estacionado en la calle (prácticamente en la puerta del edificio).  El entorno es muy agradable y seguro.  Muy recomendable!","created_at":"2016-01-27T14:38:57Z","id":60805001,"language":"es","localized_date":"Enero de 2016","response":"","reviewee":{"deleted":false,"first_name":"María Alicia Y Mauricio","host_name":"María Alicia Y Mauricio","id":28474161,"is_superhost":true,"picture_url":"https://a0.muscache.com/im/pictures/d9cd434e-f63b-4b5f-bf76-07ac7709ab6d.jpg?aki_policy=profile_x_medium","profile_path":"/users/show/28474161"},"reviewer":{"deleted":false,"first_name":"Eduardo","host_name":"Eduardo","id":53212393,"is_superhost":false,"picture_url":"https://a0.muscache.com/im/pictures/user/b253f518-7948-48d6-ad92-134b4632084c.jpg?aki_policy=profile_x_medium","profile_path":"/users/show/53212393"}},{"collection_tag":null,"comments":"Cuando llegamos al depto la hermana de Mauricio nos dio la bienvenida. Muy amable y el depto en buenas condiciones. No podemos criticar nada, en pleno centro con linda vista sobre Río Cuarto. Mis padres se sentían muy cómodos. Especialmente gracias por la flexibilidad respecto al check-out! Saludos, Annette","created_at":"2016-01-11T15:07:07Z","id":59543686,"language":"es","localized_date":"Enero de 2016","response":"","reviewee":{"deleted":false,"first_name":"María Alicia Y Mauricio","host_name":"María Alicia Y Mauricio","id":28474161,"is_superhost":true,"picture_url":"https://a0.muscache.com/im/pictures/d9cd434e-f63b-4b5f-bf76-07ac7709ab6d.jpg?aki_policy=profile_x_medium","profile_path":"/users/show/28474161"},"reviewer":{"deleted":false,"first_name":"Annette","host_name":"Annette","id":26734304,"is_superhost":false,"picture_url":"https://a0.muscache.com/im/pictures/c15caa87-0575-4ad6-88b7-9240671b7188.jpg?aki_policy=profile_x_medium","profile_path":"/users/show/26734304"}},{"collection_tag":null,"comments":"Todo perfecto, tal cual se describe en el anuncio, excelente predisposición de Maria Alicia!","created_at":"2016-11-20T11:34:08Z","id":114819539,"language":"en","localized_date":"Noviembre de 2016","response":"","reviewee":{"deleted":false,"first_name":"María Alicia Y Mauricio","host_name":"María Alicia Y Mauricio","id":28474161,"is_superhost":true,"picture_url":"https://a0.muscache.com/im/pictures/d9cd434e-f63b-4b5f-bf76-07ac7709ab6d.jpg?aki_policy=profile_x_medium","profile_path":"/users/show/28474161"},"reviewer":{"deleted":false,"first_name":"Diego","host_name":"Diego","id":100521341,"is_superhost":false,"picture_url":"https://a0.muscache.com/im/pictures/156df417-f1d6-4a56-9020-698e56d8e96c.jpg?aki_policy=profile_x_medium","profile_path":"/users/show/100521341"}},{"collection_tag":null,"comments":"It was a pleasure stay here! Communication with the owners was always really good and fluent. Great place to discover the city. ","created_at":"2017-01-14T11:37:09Z","id":126767566,"language":"en","localized_date":"Enero de 2017","response":"","reviewee":{"deleted":false,"first_name":"María Alicia Y Mauricio","host_name":"María Alicia Y Mauricio","id":28474161,"is_superhost":true,"picture_url":"https://a0.muscache.com/im/pictures/d9cd434e-f63b-4b5f-bf76-07ac7709ab6d.jpg?aki_policy=profile_x_medium","profile_path":"/users/show/28474161"},"reviewer":{"deleted":false,"first_name":"Stefan","host_name":"Stefan","id":16327215,"is_superhost":false,"picture_url":"https://a0.muscache.com/im/pictures/67d51e11-82c2-49e0-b673-362ca041b08b.jpg?aki_policy=profile_x_medium","profile_path":"/users/show/16327215"}}],"metadata":{"reviews_count":25,"should_show_review_translations":true}}